{
  "progressType": "dots",
  "passPercentage": 100,
  "questions": [
    {
      "params": {
        "answers": [
          {
            "correct": true,
            "tipsAndFeedback": {
              "tip": "",
              "chosenFeedback": "",
              "notChosenFeedback": ""
            },
            "text": "\u003cdiv\u003e\u003ccode\u003eS\u003csub\u003e1\u003c/sub\u003e \u003d { C, O, M, P, U, T, E, R, S, I, N }\u003c/code\u003e\u003c/div\u003e\n"
          },
          {
            "correct": false,
            "tipsAndFeedback": {
              "tip": "",
              "chosenFeedback": "",
              "notChosenFeedback": ""
            },
            "text": "\u003cdiv\u003e\u003ccode\u003eS\u003csub\u003e2\u003c/sub\u003e \u003d { C, O, M, P, U, T, E, R, S, I, N }\u003c/code\u003e\u003c/div\u003e\n"
          },
          {
            "correct": false,
            "tipsAndFeedback": {
              "tip": "",
              "chosenFeedback": "",
              "notChosenFeedback": ""
            },
            "text": "\u003cdiv\u003e\u003ccode\u003eS\u003csub\u003e3\u003c/sub\u003e \u003d { C, O, M, P, U, T, E, R, S, I, N }\u003c/code\u003e\u003c/div\u003e\n"
          },
          {
            "correct": false,
            "tipsAndFeedback": {
              "tip": "",
              "chosenFeedback": "",
              "notChosenFeedback": ""
            },
            "text": "\u003cdiv\u003e\u003ccode\u003eS\u003csub\u003e1\u003c/sub\u003e \u003d { O, M, P, U, T, R }\u003c/code\u003e\u003c/div\u003e\n"
          },
          {
            "correct": false,
            "tipsAndFeedback": {
              "tip": "",
              "chosenFeedback": "",
              "notChosenFeedback": ""
            },
            "text": "\u003cdiv\u003e\u003ccode\u003eS\u003csub\u003e2\u003c/sub\u003e \u003d { O, M, P, U, T, R }\u003c/code\u003e\u003c/div\u003e\n"
          },
          {
            "correct": false,
            "tipsAndFeedback": {
              "tip": "",
              "chosenFeedback": "",
              "notChosenFeedback": ""
            },
            "text": "\u003cdiv\u003e\u003ccode\u003eS\u003csub\u003e1\u003c/sub\u003e \u003d { C, O, M, P, U, T, E, R, S, C, I, E, N }\u003c/code\u003e\u003c/div\u003e\n"
          }
        ],
        "overallFeedback": [
          {
            "from": 0,
            "to": 99,
            "feedback": "Please review the course materials."
          },
          {
            "from": 100,
            "to": 100,
            "feedback": "Excellent!"
          }
        ],
        "behaviour": {
          "enableRetry": true,
          "enableSolutionsButton": false,
          "enableCheckButton": true,
          "type": "multi",
          "singlePoint": true,
          "randomAnswers": true,
          "showSolutionsRequiresInput": true,
          "disableImageZooming": false,
          "confirmCheckDialog": false,
          "confirmRetryDialog": false,
          "autoCheck": false,
          "passPercentage": 100,
          "showScorePoints": true
        },
        "UI": {
          "checkAnswerButton": "Check",
          "showSolutionButton": "Show solution",
          "tryAgainButton": "Retry",
          "tipsLabel": "Show tip",
          "scoreBarLabel": "You got :num out of :total points",
          "tipAvailable": "Tip available",
          "feedbackAvailable": "Feedback available",
          "readFeedback": "Read feedback",
          "wrongAnswer": "Wrong answer",
          "correctAnswer": "Correct answer",
          "shouldCheck": "Should have been checked",
          "shouldNotCheck": "Should not have been checked",
          "noInput": "Please answer before viewing the solution"
        },
        "confirmCheck": {
          "header": "Finish ?",
          "body": "Are you sure you wish to finish ?",
          "cancelLabel": "Cancel",
          "confirmLabel": "Finish"
        },
        "confirmRetry": {
          "header": "Retry ?",
          "body": "Are you sure you wish to retry ?",
          "cancelLabel": "Cancel",
          "confirmLabel": "Confirm"
        },
        "question": "\u003cp\u003eGiven the following sets:\u003cbr\u003e\u003ccode\u003eS\u003csub\u003e1\u003c/sub\u003e \u003d { C, O, M, P, U, T, E, R }\u003cbr\u003eS\u003csub\u003e2\u003c/sub\u003e \u003d { S, C, I, E, N }\u003cbr\u003eS\u003csub\u003e3\u003c/sub\u003e \u003d { E, N, G, I, R }\u003c/code\u003e\u003cbr\u003eWhat is the result of \u003ccode\u003eS\u003csub\u003e1\u003c/sub\u003e.addAll(S\u003csub\u003e2\u003c/sub\u003e)\u003c/code\u003e?\u003c/p\u003e\n",
        "media": {
          "library": "H5P.Image 1.1",
          "params": {}
        }
      },
      "library": "H5P.MultiChoice 1.13"
    },
    {
      "params": {
        "answers": [
          {
            "correct": true,
            "tipsAndFeedback": {
              "tip": "",
              "chosenFeedback": "",
              "notChosenFeedback": ""
            },
            "text": "\u003cdiv\u003e\u003ccode\u003eS\u003csub\u003e2\u003c/sub\u003e \u003d { I, E, N }\u003c/code\u003e\u003c/div\u003e\n"
          },
          {
            "correct": false,
            "tipsAndFeedback": {
              "tip": "",
              "chosenFeedback": "",
              "notChosenFeedback": ""
            },
            "text": "\u003cdiv\u003e\u003ccode\u003eS\u003csub\u003e3\u003c/sub\u003e \u003d { I, E, N }\u003c/code\u003e\u003c/div\u003e\n"
          },
          {
            "correct": false,
            "tipsAndFeedback": {
              "tip": "",
              "chosenFeedback": "",
              "notChosenFeedback": ""
            },
            "text": "\u003cdiv\u003e\u003ccode\u003eS\u003csub\u003e2\u003c/sub\u003e \u003d { S, C }\u003c/code\u003e\u003c/div\u003e\n"
          },
          {
            "correct": false,
            "tipsAndFeedback": {
              "tip": "",
              "chosenFeedback": "",
              "notChosenFeedback": ""
            },
            "text": "\u003cdiv\u003e\u003ccode\u003eS\u003csub\u003e3\u003c/sub\u003e \u003d { S, C }\u003c/code\u003e\u003c/div\u003e\n"
          },
          {
            "correct": false,
            "tipsAndFeedback": {
              "tip": "",
              "chosenFeedback": "",
              "notChosenFeedback": ""
            },
            "text": "\u003cdiv\u003e\u003ccode\u003eS\u003csub\u003e1\u003c/sub\u003e \u003d { C, E, R }\u003c/code\u003e\u003c/div\u003e\n"
          }
        ],
        "overallFeedback": [
          {
            "from": 0,
            "to": 99,
            "feedback": "Please review the course materials."
          },
          {
            "from": 100,
            "to": 100,
            "feedback": "Excellent!"
          }
        ],
        "behaviour": {
          "enableRetry": true,
          "enableSolutionsButton": false,
          "enableCheckButton": true,
          "type": "multi",
          "singlePoint": true,
          "randomAnswers": true,
          "showSolutionsRequiresInput": true,
          "disableImageZooming": false,
          "confirmCheckDialog": false,
          "confirmRetryDialog": false,
          "autoCheck": false,
          "passPercentage": 100,
          "showScorePoints": true
        },
        "UI": {
          "checkAnswerButton": "Check",
          "showSolutionButton": "Show solution",
          "tryAgainButton": "Retry",
          "tipsLabel": "Show tip",
          "scoreBarLabel": "You got :num out of :total points",
          "tipAvailable": "Tip available",
          "feedbackAvailable": "Feedback available",
          "readFeedback": "Read feedback",
          "wrongAnswer": "Wrong answer",
          "correctAnswer": "Correct answer",
          "shouldCheck": "Should have been checked",
          "shouldNotCheck": "Should not have been checked",
          "noInput": "Please answer before viewing the solution"
        },
        "confirmCheck": {
          "header": "Finish ?",
          "body": "Are you sure you wish to finish ?",
          "cancelLabel": "Cancel",
          "confirmLabel": "Finish"
        },
        "confirmRetry": {
          "header": "Retry ?",
          "body": "Are you sure you wish to retry ?",
          "cancelLabel": "Cancel",
          "confirmLabel": "Confirm"
        },
        "question": "\u003cp\u003eGiven the following sets:\u003cbr\u003e\u003ccode\u003eS\u003csub\u003e1\u003c/sub\u003e \u003d { C, O, M, P, U, T, E, R }\u003cbr\u003eS\u003csub\u003e2\u003c/sub\u003e \u003d { S, C, I, E, N }\u003cbr\u003eS\u003csub\u003e3\u003c/sub\u003e \u003d { E, N, G, I, R }\u003c/code\u003e\u003cbr\u003eWhat is the result of \u003ccode\u003eS\u003csub\u003e2\u003c/sub\u003e.retainAll(S\u003csub\u003e3\u003c/sub\u003e)\u003c/code\u003e?\u003c/p\u003e\n",
        "media": {
          "library": "H5P.Image 1.1",
          "params": {}
        }
      },
      "library": "H5P.MultiChoice 1.13"
    },
    {
      "params": {
        "answers": [
          {
            "correct": true,
            "tipsAndFeedback": {
              "tip": "",
              "chosenFeedback": "",
              "notChosenFeedback": ""
            },
            "text": "\u003cdiv\u003e\u003ccode\u003eS\u003csub\u003e3\u003c/sub\u003e \u003d { N, G, I }\u003c/code\u003e\u003c/div\u003e\n"
          },
          {
            "correct": false,
            "tipsAndFeedback": {
              "tip": "",
              "chosenFeedback": "",
              "notChosenFeedback": ""
            },
            "text": "\u003cdiv\u003e\u003ccode\u003eS\u003csub\u003e1\u003c/sub\u003e \u003d { N, G, I }\u003c/code\u003e\u003c/div\u003e\n"
          },
          {
            "correct": false,
            "tipsAndFeedback": {
              "tip": "",
              "chosenFeedback": "",
              "notChosenFeedback": ""
            },
            "text": "\u003cdiv\u003e\u003ccode\u003eS\u003csub\u003e3\u003c/sub\u003e \u003d { E, N, G, I, R, C, O, M, P, U, T }\u003c/code\u003e\u003c/div\u003e\n"
          },
          {
            "correct": false,
            "tipsAndFeedback": {
              "tip": "",
              "chosenFeedback": "",
              "notChosenFeedback": ""
            },
            "text": "\u003cdiv\u003e\u003ccode\u003eS\u003csub\u003e1\u003c/sub\u003e \u003d { E, N, G, I, R, C, O, M, P, U, T }\u003c/code\u003e\u003c/div\u003e\n"
          }
        ],
        "overallFeedback": [
          {
            "from": 0,
            "to": 99,
            "feedback": "Please review the course materials."
          },
          {
            "from": 100,
            "to": 100,
            "feedback": "Excellent!"
          }
        ],
        "behaviour": {
          "enableRetry": true,
          "enableSolutionsButton": false,
          "enableCheckButton": true,
          "type": "multi",
          "singlePoint": true,
          "randomAnswers": true,
          "showSolutionsRequiresInput": true,
          "disableImageZooming": false,
          "confirmCheckDialog": false,
          "confirmRetryDialog": false,
          "autoCheck": false,
          "passPercentage": 100,
          "showScorePoints": true
        },
        "UI": {
          "checkAnswerButton": "Check",
          "showSolutionButton": "Show solution",
          "tryAgainButton": "Retry",
          "tipsLabel": "Show tip",
          "scoreBarLabel": "You got :num out of :total points",
          "tipAvailable": "Tip available",
          "feedbackAvailable": "Feedback available",
          "readFeedback": "Read feedback",
          "wrongAnswer": "Wrong answer",
          "correctAnswer": "Correct answer",
          "shouldCheck": "Should have been checked",
          "shouldNotCheck": "Should not have been checked",
          "noInput": "Please answer before viewing the solution"
        },
        "confirmCheck": {
          "header": "Finish ?",
          "body": "Are you sure you wish to finish ?",
          "cancelLabel": "Cancel",
          "confirmLabel": "Finish"
        },
        "confirmRetry": {
          "header": "Retry ?",
          "body": "Are you sure you wish to retry ?",
          "cancelLabel": "Cancel",
          "confirmLabel": "Confirm"
        },
        "question": "\u003cp\u003eGiven the following sets:\u003cbr\u003e\u003ccode\u003eS\u003csub\u003e1\u003c/sub\u003e \u003d { C, O, M, P, U, T, E, R }\u003cbr\u003eS\u003csub\u003e2\u003c/sub\u003e \u003d { S, C, I, E, N }\u003cbr\u003eS\u003csub\u003e3\u003c/sub\u003e \u003d { E, N, G, I, R }\u003c/code\u003e\u003cbr\u003eWhat is the result of \u003ccode\u003eS\u003csub\u003e3\u003c/sub\u003e.removeAll(S\u003csub\u003e1\u003c/sub\u003e)\u003c/code\u003e?\u003c/p\u003e\n",
        "media": {
          "library": "H5P.Image 1.1",
          "params": {}
        }
      },
      "library": "H5P.MultiChoice 1.13"
    }
  ],
  "introPage": {
    "showIntroPage": false,
    "startButtonText": "Start Quiz",
    "introduction": ""
  },
  "texts": {
    "prevButton": "Previous",
    "nextButton": "Next",
    "finishButton": "Finish",
    "textualProgress": "Question: @current of @total questions",
    "questionLabel": "Question",
    "jumpToQuestion": "Jump to question %d",
    "readSpeakerProgress": "Question @current of @total",
    "unansweredText": "Unanswered",
    "answeredText": "Answered",
    "currentQuestionText": "Current question"
  },
  "endGame": {
    "showResultPage": true,
    "solutionButtonText": "Show solution",
    "finishButtonText": "Finish",
    "showAnimations": false,
    "skippable": false,
    "skipButtonText": "Skip video",
    "message": "Your result:",
    "retryButtonText": "Retry",
    "noResultMessage": "Finished",
    "overallFeedback": [
      {
        "from": 0,
        "to": 100,
        "feedback": "You got @score points of @total possible."
      }
    ],
    "oldFeedback": {
      "successGreeting": "Congratulations!",
      "successComment": "Excellent work!",
      "failGreeting": "Oh, no!",
      "failComment": "Please review the lab and/or course materials, visit office hours, or post on Piazza."
    },
    "showSolutionButton": false
  },
  "override": {
    "showSolutionButton": "off",
    "retryButton": "off",
    "checkButton": true
  },
  "disableBackwardsNavigation": false,
  "randomQuestions": false
}
